{
  "app": {
    "[project]/nextjs-site/app/_not-found/page": [
      "static/media/83afe278b6a6bb3c-s.p.3a6ba036.woff2"
    ],
    "[project]/nextjs-site/app/about/page": [
      "static/media/83afe278b6a6bb3c-s.p.3a6ba036.woff2"
    ],
    "[project]/nextjs-site/app/blog/page": [
      "static/media/83afe278b6a6bb3c-s.p.3a6ba036.woff2"
    ],
    "[project]/nextjs-site/app/clients/page": [
      "static/media/83afe278b6a6bb3c-s.p.3a6ba036.woff2"
    ],
    "[project]/nextjs-site/app/contact/page": [
      "static/media/83afe278b6a6bb3c-s.p.3a6ba036.woff2"
    ],
    "[project]/nextjs-site/app/page": [
      "static/media/83afe278b6a6bb3c-s.p.3a6ba036.woff2"
    ],
    "[project]/nextjs-site/app/process/page": [
      "static/media/83afe278b6a6bb3c-s.p.3a6ba036.woff2"
    ],
    "[project]/nextjs-site/app/projects/page": [
      "static/media/83afe278b6a6bb3c-s.p.3a6ba036.woff2"
    ],
    "[project]/nextjs-site/app/services/page": [
      "static/media/83afe278b6a6bb3c-s.p.3a6ba036.woff2"
    ]
  },
  "appUsingSizeAdjust": true,
  "pages": {},
  "pagesUsingSizeAdjust": false
}